LICENSE
MANIFEST.in
setup.py
versiontools_support.py
taiga_contrib_github_auth/__init__.py
taiga_contrib_github_auth/apps.py
taiga_contrib_github_auth/connector.py
taiga_contrib_github_auth/services.py
taiga_contrib_github_auth.egg-info/PKG-INFO
taiga_contrib_github_auth.egg-info/SOURCES.txt
taiga_contrib_github_auth.egg-info/dependency_links.txt
taiga_contrib_github_auth.egg-info/top_level.txt
tests/__init__.py
tests/factories.py
tests/settings.py
tests/integration/__init__.py
tests/integration/test_auth_api.py
tests/unit/__init__.py
tests/unit/test_connectors_github.py