Metadata-Version: 1.1
Name: taiga-contrib-github-auth
Version: 3.0
Summary: The Taiga plugin for github authentication
Home-page: https://github.com/taigaio/taiga-contrib-github-auth
Author: Jesús Espino García
Author-email: jesus.espino@kaleidos.net
License: AGPL
Keywords: taiga,github,auth,plugin
Platform: UNKNOWN
Classifier: Programming Language :: Python
Classifier: Development Status :: 4 - Beta
Classifier: Framework :: Django
Classifier: Intended Audience :: Developers
Classifier: License :: OSI Approved :: GNU Affero General Public License v3
Classifier: Operating System :: OS Independent
Classifier: Programming Language :: Python
Classifier: Topic :: Internet :: WWW/HTTP
